{"sg":{"word":"sg","etymologies":[{"partsOfSpeech":[{"partOfSpeech":"Adjective","senses":[{"sense":"Abbreviation of singular.","date":"","examples":[]}]}]}]},"sgabelli":{"word":"sgabelli","etymologies":[{"partsOfSpeech":[{"partOfSpeech":"Noun","senses":[{"sense":"plural of sgabello","date":"","examples":[]}]}]}]},"sgabello":{"word":"sgabello","etymologies":[{"partsOfSpeech":[{"partOfSpeech":"Noun","senses":[{"sense":"A kind of stool typical of the Italian Renaissance, typically made of walnut and having a variety of carvings and turned elements.","date":"","examples":[]}]}]}]},"sgabellos":{"word":"sgabellos","etymologies":[{"partsOfSpeech":[{"partOfSpeech":"Noun","senses":[{"sense":"plural of sgabello","date":"","examples":[]}]}]}]},"sgraffiato":{"word":"sgraffiato","etymologies":[{"partsOfSpeech":[{"partOfSpeech":"Noun","senses":[{"sense":"Alternative form of sgraffito","date":"","examples":[]}]}]}]},"sgraffiti":{"word":"sgraffiti","etymologies":[{"partsOfSpeech":[{"partOfSpeech":"Noun","senses":[{"sense":"plural of sgraffito","date":"","examples":[]}]}]}]},"sgraffito":{"word":"sgraffito","etymologies":[{"partsOfSpeech":[{"partOfSpeech":"Noun","senses":[{"sense":"(art, uncountable) A technique in ceramics, art and wall design, where the top layer of pigment or slip is scratched through to reveal an underlying layer.","date":"","examples":[]},{"sense":"(art, countable) An instance or sample of sgraffito.","date":"","examples":[]}]},{"partOfSpeech":"Verb","senses":[{"sense":"(art) To produce a design using this technique.","date":"","examples":[]}]}]}]}}